asr_app/app.py
asr_app/io.py
asr_app/progress.py
asr_app/settings.py
asr_app/texts.py
asr_app-0.5.0.dist-info/METADATA
asr_app-0.5.0.dist-info/WHEEL
asr_app-0.5.0.dist-info/entry_points.txt
asr_app-0.5.0.dist-info/RECORD
